jsontools/__init__.py
jsontools/jsontools.py
jsontools/random_data.py
pyjsontools-0.1.2.dist-info/LICENSE
pyjsontools-0.1.2.dist-info/METADATA
pyjsontools-0.1.2.dist-info/WHEEL
pyjsontools-0.1.2.dist-info/top_level.txt
pyjsontools-0.1.2.dist-info/RECORD
