Metadata-Version: 2.1
Name: pyjsontools
Version: 0.1.2
Summary: Tools to edit and manipulate JSON formatted data
Author-email: "Santiago B. Perez Pita" <santibreo@gmail.com>
License: GNU GENERAL PUBLIC LICENSE
Project-URL: Repository, https://github.com/santibreo/jsontools
Project-URL: Documentation, https://santibreo.github.io/jsontools/index.html
Keywords: json,itertools
Classifier: Development Status :: 4 - Beta
Classifier: Topic :: File Formats :: JSON
Classifier: Topic :: File Formats :: JSON :: JSON Schema
Requires-Python: >=3.9
License-File: LICENSE
